{
    "855": {
        "name": "Vĩnh Long",
        "type": "thanh-pho",
        "name_with_type": "Thành phố Vĩnh Long",
        "code": "855",
        "parent_code": "86"
    },
    "857": {
        "name": "Long Hồ",
        "type": "huyen",
        "name_with_type": "Huyện Long Hồ",
        "code": "857",
        "parent_code": "86"
    },
    "858": {
        "name": "Mang Thít",
        "type": "huyen",
        "name_with_type": "Huyện Mang Thít",
        "code": "858",
        "parent_code": "86"
    },
    "859": {
        "name": "Vũng Liêm",
        "type": "huyen",
        "name_with_type": "Huyện  Vũng Liêm",
        "code": "859",
        "parent_code": "86"
    },
    "860": {
        "name": "Tam Bình",
        "type": "huyen",
        "name_with_type": "Huyện Tam Bình",
        "code": "860",
        "parent_code": "86"
    },
    "861": {
        "name": "Bình Minh",
        "type": "thi-xa",
        "name_with_type": "Thị xã Bình Minh",
        "code": "861",
        "parent_code": "86"
    },
    "862": {
        "name": "Trà Ôn",
        "type": "huyen",
        "name_with_type": "Huyện Trà Ôn",
        "code": "862",
        "parent_code": "86"
    },
    "863": {
        "name": "Bình Tân",
        "type": "huyen",
        "name_with_type": "Huyện Bình Tân",
        "code": "863",
        "parent_code": "86"
    }
}