[
    {
        "WARDS_ID": 5967,
        "WARDS_NAME": "THỊ TRẤN ĐÀ BẮC",
        "DISTRICT_ID": 331
    },
    {
        "WARDS_ID": 5968,
        "WARDS_NAME": "XÃ MƯỜNG CHIỀNG",
        "DISTRICT_ID": 331
    },
    {
        "WARDS_ID": 5969,
        "WARDS_NAME": "XÃ TÂN PHEO",
        "DISTRICT_ID": 331
    },
    {
        "WARDS_ID": 5970,
        "WARDS_NAME": "XÃ ĐỒNG RUỘNG",
        "DISTRICT_ID": 331
    },
    {
        "WARDS_ID": 5971,
        "WARDS_NAME": "XÃ GIÁP ĐẮT",
        "DISTRICT_ID": 331
    },
    {
        "WARDS_ID": 5972,
        "WARDS_NAME": "XÃ ĐỒNG NGHÊ",
        "DISTRICT_ID": 331
    },
    {
        "WARDS_ID": 5973,
        "WARDS_NAME": "XÃ SUỐI NÁNH",
        "DISTRICT_ID": 331
    },
    {
        "WARDS_ID": 5974,
        "WARDS_NAME": "XÃ MƯỜNG TUỔNG",
        "DISTRICT_ID": 331
    },
    {
        "WARDS_ID": 5975,
        "WARDS_NAME": "XÃ ĐỒNG CHUM",
        "DISTRICT_ID": 331
    },
    {
        "WARDS_ID": 5976,
        "WARDS_NAME": "XÃ ĐOÀN KẾT",
        "DISTRICT_ID": 331
    },
    {
        "WARDS_ID": 5977,
        "WARDS_NAME": "XÃ TÂN MINH",
        "DISTRICT_ID": 331
    },
    {
        "WARDS_ID": 5978,
        "WARDS_NAME": "XÃ TRUNG THÀNH",
        "DISTRICT_ID": 331
    },
    {
        "WARDS_ID": 5979,
        "WARDS_NAME": "XÃ YÊN HÒA",
        "DISTRICT_ID": 331
    },
    {
        "WARDS_ID": 5980,
        "WARDS_NAME": "XÃ CAO SƠN",
        "DISTRICT_ID": 331
    },
    {
        "WARDS_ID": 5981,
        "WARDS_NAME": "XÃ TIỀN PHONG",
        "DISTRICT_ID": 331
    },
    {
        "WARDS_ID": 5982,
        "WARDS_NAME": "XÃ VẦY NƯA",
        "DISTRICT_ID": 331
    },
    {
        "WARDS_ID": 5983,
        "WARDS_NAME": "XÃ HÀO LÝ",
        "DISTRICT_ID": 331
    },
    {
        "WARDS_ID": 5984,
        "WARDS_NAME": "XÃ TU LÝ",
        "DISTRICT_ID": 331
    },
    {
        "WARDS_ID": 5985,
        "WARDS_NAME": "XÃ HIỀN LƯƠNG",
        "DISTRICT_ID": 331
    },
    {
        "WARDS_ID": 5986,
        "WARDS_NAME": "XÃ TOÀN SƠN",
        "DISTRICT_ID": 331
    },
    {
        "WARDS_ID": 26330,
        "WARDS_NAME": "XÃ NÁNH NGHÊ",
        "DISTRICT_ID": 331
    }
]