[
    {
        "WARDS_ID": 7602,
        "WARDS_NAME": "XÃ YÊN HÓA",
        "DISTRICT_ID": 400
    },
    {
        "WARDS_ID": 7603,
        "WARDS_NAME": "THỊ TRẤN QUY ĐẠT",
        "DISTRICT_ID": 400
    },
    {
        "WARDS_ID": 7604,
        "WARDS_NAME": "XÃ XUÂN HÓA",
        "DISTRICT_ID": 400
    },
    {
        "WARDS_ID": 7605,
        "WARDS_NAME": "XÃ TRUNG HÓA",
        "DISTRICT_ID": 400
    },
    {
        "WARDS_ID": 7606,
        "WARDS_NAME": "XÃ TÂN HÓA",
        "DISTRICT_ID": 400
    },
    {
        "WARDS_ID": 7607,
        "WARDS_NAME": "XÃ MINH HÓA",
        "DISTRICT_ID": 400
    },
    {
        "WARDS_ID": 7608,
        "WARDS_NAME": "XÃ HỒNG HÓA",
        "DISTRICT_ID": 400
    },
    {
        "WARDS_ID": 7609,
        "WARDS_NAME": "XÃ HÓA TIẾN",
        "DISTRICT_ID": 400
    },
    {
        "WARDS_ID": 7610,
        "WARDS_NAME": "XÃ HÓA HỢP",
        "DISTRICT_ID": 400
    },
    {
        "WARDS_ID": 7611,
        "WARDS_NAME": "XÃ HÓA PHÚC",
        "DISTRICT_ID": 400
    },
    {
        "WARDS_ID": 7612,
        "WARDS_NAME": "XÃ HÓA THANH",
        "DISTRICT_ID": 400
    },
    {
        "WARDS_ID": 7613,
        "WARDS_NAME": "XÃ DÂN HÓA",
        "DISTRICT_ID": 400
    },
    {
        "WARDS_ID": 7614,
        "WARDS_NAME": "XÃ THƯỢNG HÓA",
        "DISTRICT_ID": 400
    },
    {
        "WARDS_ID": 7615,
        "WARDS_NAME": "XÃ TRỌNG HÓA",
        "DISTRICT_ID": 400
    },
    {
        "WARDS_ID": 7616,
        "WARDS_NAME": "XÃ QUY HÓA",
        "DISTRICT_ID": 400
    },
    {
        "WARDS_ID": 7617,
        "WARDS_NAME": "XÃ HÓA SƠN",
        "DISTRICT_ID": 400
    }
]