[
    {
        "WARDS_ID": 9732,
        "WARDS_NAME": "XÃ PHƯỚC CHỈ",
        "DISTRICT_ID": 561
    },
    {
        "WARDS_ID": 9733,
        "WARDS_NAME": "XÃ AN HOÀ",
        "DISTRICT_ID": 561
    },
    {
        "WARDS_ID": 9734,
        "WARDS_NAME": "THỊ TRẤN TRẢNG BÀNG",
        "DISTRICT_ID": 561
    },
    {
        "WARDS_ID": 9735,
        "WARDS_NAME": "XÃ AN TỊNH",
        "DISTRICT_ID": 561
    },
    {
        "WARDS_ID": 9736,
        "WARDS_NAME": "XÃ BÌNH THẠNH",
        "DISTRICT_ID": 561
    },
    {
        "WARDS_ID": 9737,
        "WARDS_NAME": "XÃ ĐÔN THUẬN",
        "DISTRICT_ID": 561
    },
    {
        "WARDS_ID": 9738,
        "WARDS_NAME": "XÃ GIA BÌNH",
        "DISTRICT_ID": 561
    },
    {
        "WARDS_ID": 9739,
        "WARDS_NAME": "XÃ GIA LỘC",
        "DISTRICT_ID": 561
    },
    {
        "WARDS_ID": 9740,
        "WARDS_NAME": "XÃ HƯNG THUẬN",
        "DISTRICT_ID": 561
    },
    {
        "WARDS_ID": 9741,
        "WARDS_NAME": "XÃ LỘC HƯNG",
        "DISTRICT_ID": 561
    },
    {
        "WARDS_ID": 9742,
        "WARDS_NAME": "XÃ PHƯỚC LƯU",
        "DISTRICT_ID": 561
    },
    {
        "WARDS_ID": 26144,
        "WARDS_NAME": "XÃ PHƯỚC BÌNH",
        "DISTRICT_ID": 561
    }
]