[
    {
        "WARDS_ID": 10683,
        "WARDS_NAME": "XÃ PHÚ HỘI",
        "DISTRICT_ID": 634
    },
    {
        "WARDS_ID": 10684,
        "WARDS_NAME": "XÃ PHƯỚC HƯNG",
        "DISTRICT_ID": 634
    },
    {
        "WARDS_ID": 10685,
        "WARDS_NAME": "XÃ VĨNH LỘC",
        "DISTRICT_ID": 634
    },
    {
        "WARDS_ID": 10686,
        "WARDS_NAME": "XÃ VĨNH HẬU",
        "DISTRICT_ID": 634
    },
    {
        "WARDS_ID": 10687,
        "WARDS_NAME": "XÃ VĨNH TRƯỜNG",
        "DISTRICT_ID": 634
    },
    {
        "WARDS_ID": 10688,
        "WARDS_NAME": "XÃ VĨNH HỘI ĐÔNG",
        "DISTRICT_ID": 634
    },
    {
        "WARDS_ID": 10689,
        "WARDS_NAME": "XÃ ĐA PHƯỚC",
        "DISTRICT_ID": 634
    },
    {
        "WARDS_ID": 10690,
        "WARDS_NAME": "THỊ TRẤN AN PHÚ",
        "DISTRICT_ID": 634
    },
    {
        "WARDS_ID": 10691,
        "WARDS_NAME": "THỊ TRẤN LONG BÌNH",
        "DISTRICT_ID": 634
    },
    {
        "WARDS_ID": 10692,
        "WARDS_NAME": "XÃ KHÁNH AN",
        "DISTRICT_ID": 634
    },
    {
        "WARDS_ID": 10693,
        "WARDS_NAME": "XÃ KHÁNH BÌNH",
        "DISTRICT_ID": 634
    },
    {
        "WARDS_ID": 10694,
        "WARDS_NAME": "XÃ QUỐC THÁI",
        "DISTRICT_ID": 634
    },
    {
        "WARDS_ID": 10695,
        "WARDS_NAME": "XÃ NHƠN HỘI",
        "DISTRICT_ID": 634
    },
    {
        "WARDS_ID": 10696,
        "WARDS_NAME": "XÃ PHÚ HỮU",
        "DISTRICT_ID": 634
    }
]