{
    "17932": {
        "name": "Nam Hưng",
        "type": "xa",
        "name_with_type": "Xã Nam Hưng",
        "code": "17932",
        "parent_code": "430"
    },
    "17935": {
        "name": "Nam Nghĩa",
        "type": "xa",
        "name_with_type": "Xã Nam Nghĩa",
        "code": "17935",
        "parent_code": "430"
    },
    "17938": {
        "name": "Nam Thanh",
        "type": "xa",
        "name_with_type": "Xã Nam Thanh",
        "code": "17938",
        "parent_code": "430"
    },
    "17941": {
        "name": "Nam Anh",
        "type": "xa",
        "name_with_type": "Xã Nam Anh",
        "code": "17941",
        "parent_code": "430"
    },
    "17944": {
        "name": "Nam Xuân",
        "type": "xa",
        "name_with_type": "Xã Nam Xuân",
        "code": "17944",
        "parent_code": "430"
    },
    "17947": {
        "name": "Nam Thái",
        "type": "xa",
        "name_with_type": "Xã Nam Thái",
        "code": "17947",
        "parent_code": "430"
    },
    "17950": {
        "name": "Nam Đàn",
        "type": "thi-tran",
        "name_with_type": "Thị trấn Nam Đàn",
        "code": "17950",
        "parent_code": "430"
    },
    "17953": {
        "name": "Nam Lĩnh",
        "type": "xa",
        "name_with_type": "Xã Nam Lĩnh",
        "code": "17953",
        "parent_code": "430"
    },
    "17956": {
        "name": "Nam Giang",
        "type": "xa",
        "name_with_type": "Xã Nam Giang",
        "code": "17956",
        "parent_code": "430"
    },
    "17959": {
        "name": "Xuân Hòa",
        "type": "xa",
        "name_with_type": "Xã Xuân Hòa",
        "code": "17959",
        "parent_code": "430"
    },
    "17962": {
        "name": "Hùng Tiến",
        "type": "xa",
        "name_with_type": "Xã Hùng Tiến",
        "code": "17962",
        "parent_code": "430"
    },
    "17968": {
        "name": "Thượng Tân Lộc",
        "type": "xa",
        "name_with_type": "Xã Thượng Tân Lộc",
        "code": "17968",
        "parent_code": "430"
    },
    "17971": {
        "name": "Kim Liên",
        "type": "xa",
        "name_with_type": "Xã Kim Liên",
        "code": "17971",
        "parent_code": "430"
    },
    "17977": {
        "name": "Hồng Long",
        "type": "xa",
        "name_with_type": "Xã Hồng Long",
        "code": "17977",
        "parent_code": "430"
    },
    "17980": {
        "name": "Xuân Lâm",
        "type": "xa",
        "name_with_type": "Xã Xuân Lâm",
        "code": "17980",
        "parent_code": "430"
    },
    "17983": {
        "name": "Nam Cát",
        "type": "xa",
        "name_with_type": "Xã Nam Cát",
        "code": "17983",
        "parent_code": "430"
    },
    "17986": {
        "name": "Khánh Sơn",
        "type": "xa",
        "name_with_type": "Xã Khánh Sơn",
        "code": "17986",
        "parent_code": "430"
    },
    "17989": {
        "name": "Trung Phúc Cường",
        "type": "xa",
        "name_with_type": "Xã Trung Phúc Cường",
        "code": "17989",
        "parent_code": "430"
    },
    "17998": {
        "name": "Nam Kim",
        "type": "xa",
        "name_with_type": "Xã Nam Kim",
        "code": "17998",
        "parent_code": "430"
    }
}