{
    "27931": {
        "name": "Hậu Nghĩa",
        "type": "thi-tran",
        "name_with_type": "Thị trấn Hậu Nghĩa",
        "code": "27931",
        "parent_code": "802"
    },
    "27934": {
        "name": "Hiệp Hòa",
        "type": "thi-tran",
        "name_with_type": "Thị trấn Hiệp Hòa",
        "code": "27934",
        "parent_code": "802"
    },
    "27937": {
        "name": "Đức Hòa",
        "type": "thi-tran",
        "name_with_type": "Thị trấn Đức Hòa",
        "code": "27937",
        "parent_code": "802"
    },
    "27940": {
        "name": "Lộc Giang",
        "type": "xa",
        "name_with_type": "Xã Lộc Giang",
        "code": "27940",
        "parent_code": "802"
    },
    "27943": {
        "name": "An Ninh Đông",
        "type": "xa",
        "name_with_type": "Xã An Ninh Đông",
        "code": "27943",
        "parent_code": "802"
    },
    "27946": {
        "name": "An Ninh Tây",
        "type": "xa",
        "name_with_type": "Xã An Ninh Tây",
        "code": "27946",
        "parent_code": "802"
    },
    "27949": {
        "name": "Tân Mỹ",
        "type": "xa",
        "name_with_type": "Xã Tân Mỹ",
        "code": "27949",
        "parent_code": "802"
    },
    "27952": {
        "name": "Hiệp Hòa",
        "type": "xa",
        "name_with_type": "Xã Hiệp Hòa",
        "code": "27952",
        "parent_code": "802"
    },
    "27955": {
        "name": "Đức Lập Thượng",
        "type": "xa",
        "name_with_type": "Xã Đức Lập Thượng",
        "code": "27955",
        "parent_code": "802"
    },
    "27958": {
        "name": "Đức Lập Hạ",
        "type": "xa",
        "name_with_type": "Xã Đức Lập Hạ",
        "code": "27958",
        "parent_code": "802"
    },
    "27961": {
        "name": "Tân Phú",
        "type": "xa",
        "name_with_type": "Xã Tân Phú",
        "code": "27961",
        "parent_code": "802"
    },
    "27964": {
        "name": "Mỹ Hạnh Bắc",
        "type": "xa",
        "name_with_type": "Xã Mỹ Hạnh Bắc",
        "code": "27964",
        "parent_code": "802"
    },
    "27967": {
        "name": "Đức Hòa Thượng",
        "type": "xa",
        "name_with_type": "Xã Đức Hòa Thượng",
        "code": "27967",
        "parent_code": "802"
    },
    "27970": {
        "name": "Hòa Khánh Tây",
        "type": "xa",
        "name_with_type": "Xã Hòa Khánh Tây",
        "code": "27970",
        "parent_code": "802"
    },
    "27973": {
        "name": "Hòa Khánh Đông",
        "type": "xa",
        "name_with_type": "Xã Hòa Khánh Đông",
        "code": "27973",
        "parent_code": "802"
    },
    "27976": {
        "name": "Mỹ Hạnh Nam",
        "type": "xa",
        "name_with_type": "Xã Mỹ Hạnh Nam",
        "code": "27976",
        "parent_code": "802"
    },
    "27979": {
        "name": "Hòa Khánh Nam",
        "type": "xa",
        "name_with_type": "Xã Hòa Khánh Nam",
        "code": "27979",
        "parent_code": "802"
    },
    "27982": {
        "name": "Đức Hòa Đông",
        "type": "xa",
        "name_with_type": "Xã Đức Hòa Đông",
        "code": "27982",
        "parent_code": "802"
    },
    "27985": {
        "name": "Đức Hòa Hạ",
        "type": "xa",
        "name_with_type": "Xã Đức Hòa Hạ",
        "code": "27985",
        "parent_code": "802"
    },
    "27988": {
        "name": "Hựu Thạnh",
        "type": "xa",
        "name_with_type": "Xã Hựu Thạnh",
        "code": "27988",
        "parent_code": "802"
    }
}