{
    "29050": {
        "name": "Bình Đại",
        "type": "thi-tran",
        "name_with_type": "Thị trấn Bình Đại",
        "code": "29050",
        "parent_code": "835"
    },
    "29053": {
        "name": "Tam Hiệp",
        "type": "xa",
        "name_with_type": "Xã Tam Hiệp",
        "code": "29053",
        "parent_code": "835"
    },
    "29056": {
        "name": "Long Định",
        "type": "xa",
        "name_with_type": "Xã Long Định",
        "code": "29056",
        "parent_code": "835"
    },
    "29059": {
        "name": "Long Hòa",
        "type": "xa",
        "name_with_type": "Xã Long Hòa",
        "code": "29059",
        "parent_code": "835"
    },
    "29062": {
        "name": "Phú Thuận",
        "type": "xa",
        "name_with_type": "Xã Phú Thuận",
        "code": "29062",
        "parent_code": "835"
    },
    "29065": {
        "name": "Vang Quới Tây",
        "type": "xa",
        "name_with_type": "Xã Vang Quới Tây",
        "code": "29065",
        "parent_code": "835"
    },
    "29068": {
        "name": "Vang Quới Đông",
        "type": "xa",
        "name_with_type": "Xã Vang Quới Đông",
        "code": "29068",
        "parent_code": "835"
    },
    "29071": {
        "name": "Châu Hưng",
        "type": "xa",
        "name_with_type": "Xã Châu Hưng",
        "code": "29071",
        "parent_code": "835"
    },
    "29074": {
        "name": "Phú Vang",
        "type": "xa",
        "name_with_type": "Xã Phú Vang",
        "code": "29074",
        "parent_code": "835"
    },
    "29077": {
        "name": "Lộc Thuận",
        "type": "xa",
        "name_with_type": "Xã Lộc Thuận",
        "code": "29077",
        "parent_code": "835"
    },
    "29080": {
        "name": "Định Trung",
        "type": "xa",
        "name_with_type": "Xã Định Trung",
        "code": "29080",
        "parent_code": "835"
    },
    "29083": {
        "name": "Thới Lai",
        "type": "xa",
        "name_with_type": "Xã Thới Lai",
        "code": "29083",
        "parent_code": "835"
    },
    "29086": {
        "name": "Bình Thới",
        "type": "xa",
        "name_with_type": "Xã Bình Thới",
        "code": "29086",
        "parent_code": "835"
    },
    "29089": {
        "name": "Phú Long",
        "type": "xa",
        "name_with_type": "Xã Phú Long",
        "code": "29089",
        "parent_code": "835"
    },
    "29092": {
        "name": "Bình Thắng",
        "type": "xa",
        "name_with_type": "Xã Bình Thắng",
        "code": "29092",
        "parent_code": "835"
    },
    "29095": {
        "name": "Thạnh Trị",
        "type": "xa",
        "name_with_type": "Xã Thạnh Trị",
        "code": "29095",
        "parent_code": "835"
    },
    "29098": {
        "name": "Đại Hòa Lộc",
        "type": "xa",
        "name_with_type": "Xã Đại Hòa Lộc",
        "code": "29098",
        "parent_code": "835"
    },
    "29101": {
        "name": "Thừa Đức",
        "type": "xa",
        "name_with_type": "Xã Thừa Đức",
        "code": "29101",
        "parent_code": "835"
    },
    "29104": {
        "name": "Thạnh Phước",
        "type": "xa",
        "name_with_type": "Xã Thạnh Phước",
        "code": "29104",
        "parent_code": "835"
    },
    "29107": {
        "name": "Thới Thuận",
        "type": "xa",
        "name_with_type": "Xã Thới Thuận",
        "code": "29107",
        "parent_code": "835"
    }
}